segment_everything/__init__.py
segment_everything/detect_and_segment.py
segment_everything/napari_helper.py
segment_everything/prompt_generator.py
segment_everything/py.typed
segment_everything/stacked_label_dataset.py
segment_everything/stacked_labels.py
segment_everything/weights_helper.py
segment_everything/augmentation/albumentations_helper.py
segment_everything/vendored/__init__.py
segment_everything/vendored/dice.py
segment_everything/vendored/get_object_aware.py
segment_everything/vendored/PromptGuidedDecoder/Prompt_guided_Mask_Decoder.pt
segment_everything/vendored/efficientvit/__init__.py
segment_everything/vendored/efficientvit/cls_model_zoo.py
segment_everything/vendored/efficientvit/sam_model_zoo.py
segment_everything/vendored/efficientvit/seg_model_zoo.py
segment_everything/vendored/efficientvit/apps/__init__.py
segment_everything/vendored/efficientvit/apps/setup.py
segment_everything/vendored/efficientvit/apps/data_provider/__init__.py
segment_everything/vendored/efficientvit/apps/data_provider/base.py
segment_everything/vendored/efficientvit/apps/data_provider/augment/__init__.py
segment_everything/vendored/efficientvit/apps/data_provider/augment/bbox.py
segment_everything/vendored/efficientvit/apps/data_provider/augment/color_aug.py
segment_everything/vendored/efficientvit/apps/data_provider/random_resolution/__init__.py
segment_everything/vendored/efficientvit/apps/data_provider/random_resolution/_data_loader.py
segment_everything/vendored/efficientvit/apps/data_provider/random_resolution/_data_worker.py
segment_everything/vendored/efficientvit/apps/data_provider/random_resolution/controller.py
segment_everything/vendored/efficientvit/apps/trainer/__init__.py
segment_everything/vendored/efficientvit/apps/trainer/base.py
segment_everything/vendored/efficientvit/apps/trainer/run_config.py
segment_everything/vendored/efficientvit/apps/utils/__init__.py
segment_everything/vendored/efficientvit/apps/utils/dist.py
segment_everything-0.1.0.dist-info/METADATA
segment_everything-0.1.0.dist-info/WHEEL
segment_everything-0.1.0.dist-info/licenses/LICENSE
segment_everything-0.1.0.dist-info/RECORD
