Metadata-Version: 2.3
Name: segment-everything
Version: 0.1.0
Summary: Utilities for rendering and training prompt-based and overlapping segmentation models (like SAM). 
Project-URL: homepage, https://github.com/True-North-Intelligent-Algorithms/segment-everything
Project-URL: repository, https://github.com/True-North-Intelligent-Algorithms/segment-everything
Author-email: Brian Northan <bnorthan@gmail.com>
License: BSD-3-Clause
License-File: LICENSE
Classifier: Development Status :: 3 - Alpha
Classifier: License :: OSI Approved :: BSD License
Classifier: Programming Language :: Python :: 3
Classifier: Programming Language :: Python :: 3.8
Classifier: Programming Language :: Python :: 3.9
Classifier: Programming Language :: Python :: 3.10
Classifier: Programming Language :: Python :: 3.11
Classifier: Programming Language :: Python :: 3.12
Classifier: Typing :: Typed
Requires-Python: >=3.8
Requires-Dist: gdown
Requires-Dist: magicgui
Requires-Dist: numpy
Requires-Dist: onnx
Requires-Dist: onnxsim
Requires-Dist: opencv-python
Requires-Dist: scikit-image
Requires-Dist: segment-anything
Requires-Dist: timm
Requires-Dist: torch
Requires-Dist: torchpack
Requires-Dist: torchvision
Provides-Extra: dev
Requires-Dist: ipython; extra == 'dev'
Requires-Dist: mypy; extra == 'dev'
Requires-Dist: pdbpp; extra == 'dev'
Requires-Dist: pre-commit; extra == 'dev'
Requires-Dist: rich; extra == 'dev'
Requires-Dist: ruff; extra == 'dev'
Provides-Extra: test
Requires-Dist: pytest; extra == 'test'
Requires-Dist: pytest-cov; extra == 'test'
Requires-Dist: raster-geometry; extra == 'test'
